anack/__init__.py
anack/main.py
anack/models/__init__.py
anack/models/volume.py
anack/synchronizer/__init__.py
anack/synchronizer/conf.py
anack/synchronizer/stock/__init__.py
anack/synchronizer/stock/dataset/__init__.py
anack/synchronizer/stock/dataset/base.py
anack/synchronizer/stock/dataset/baseinfo.py
anack/synchronizer/stock/dataset/calendars.py
anack/synchronizer/stock/dataset/company.py
anack/synchronizer/stock/dataset/index.py
anack/synchronizer/stock/dataset/index_pool.py
anack/synchronizer/stock/dataset/pool.py
anack/synchronizer/stock/dataset/single.py
anack/synchronizer/stock/download.py
anack/synchronizer/stock/factory.py
anack/synchronizer/tools/__init__.py
anack/synchronizer/tools/base.py
anack/synchronizer/tools/data_provider.py
anack/utils/__init__.py
anack/utils/base.py
anack/utils/stock.py
anack-0.1.1.dist-info/WHEEL
anack-0.1.1.dist-info/METADATA
anack-0.1.1.dist-info/RECORD
