Metadata-Version: 2.1
Name: anack
Version: 0.1.1
Summary: 
Author: similarface
Requires-Python: >=3.7,<4.0
Classifier: Programming Language :: Python :: 3
Classifier: Programming Language :: Python :: 3.7
Classifier: Programming Language :: Python :: 3.8
Classifier: Programming Language :: Python :: 3.9
Requires-Dist: baostock (>=0.8.8,<0.9.0)
Requires-Dist: colorama (>=0.4.4,<0.5.0)
Requires-Dist: ratelimiter (>=1.2.0,<2.0.0)
Requires-Dist: tushare (>=1.2.62,<2.0.0)
